odoo/addons/printing_auto_shipment_advice/README.rst
odoo/addons/printing_auto_shipment_advice/__init__.py
odoo/addons/printing_auto_shipment_advice/__manifest__.py
odoo/addons/printing_auto_shipment_advice/i18n/it.po
odoo/addons/printing_auto_shipment_advice/i18n/printing_auto_shipment_advice.pot
odoo/addons/printing_auto_shipment_advice/models/__init__.py
odoo/addons/printing_auto_shipment_advice/models/shipment_advice.py
odoo/addons/printing_auto_shipment_advice/models/stock_warehouse.py
odoo/addons/printing_auto_shipment_advice/readme/CONFIGURE.md
odoo/addons/printing_auto_shipment_advice/readme/CONTRIBUTORS.md
odoo/addons/printing_auto_shipment_advice/readme/DESCRIPTION.md
odoo/addons/printing_auto_shipment_advice/security/ir_rule.xml
odoo/addons/printing_auto_shipment_advice/static/description/icon.png
odoo/addons/printing_auto_shipment_advice/static/description/index.html
odoo/addons/printing_auto_shipment_advice/tests/__init__.py
odoo/addons/printing_auto_shipment_advice/tests/test_printing_auto_shipment_advice.py
odoo/addons/printing_auto_shipment_advice/views/shipment_advice.xml
odoo/addons/printing_auto_shipment_advice/views/stock_warehouse.xml
odoo_addon_printing_auto_shipment_advice-18.0.1.0.2.dist-info/METADATA
odoo_addon_printing_auto_shipment_advice-18.0.1.0.2.dist-info/WHEEL
odoo_addon_printing_auto_shipment_advice-18.0.1.0.2.dist-info/top_level.txt
odoo_addon_printing_auto_shipment_advice-18.0.1.0.2.dist-info/RECORD
